box_manager/__init__.py
box_manager/_reader.py
box_manager/_sample_data.py
box_manager/_version.py
box_manager/_widget.py
box_manager/_writer.py
box_manager/napari.yaml
box_manager/_qt/FilterImage.py
box_manager/_qt/OrganizeBox.py
box_manager/_qt/OrganizeLayer.py
box_manager/_qt/SelectMetric.py
box_manager/_qt/__init__.py
box_manager/_qt/_icons/checkmark_black.png
box_manager/_qt/_icons/checkmark_white.png
box_manager/_tests/__init__.py
box_manager/_tests/test_box.py
box_manager/_tests/test_cbox.py
box_manager/_tests/test_organizelayer.py
box_manager/_tests/test_reader.py
box_manager/_tests/test_sample_data.py
box_manager/_tests/test_widget.py
box_manager/_tests/test_writer.py
box_manager/_utils/__init__.py
box_manager/_utils/filters.py
box_manager/_utils/general.py
box_manager/io/__init__.py
box_manager/io/box.py
box_manager/io/cbox.py
box_manager/io/coords.py
box_manager/io/interface.py
box_manager/io/io_utils.py
box_manager/io/mrc.py
box_manager/io/star.py
box_manager/io/tif.py
box_manager/io/tloc.py
napari_boxmanager-0.4.14.data/scripts/napari_boxmanager
napari_boxmanager-0.4.14.dist-info/LICENSE
napari_boxmanager-0.4.14.dist-info/METADATA
napari_boxmanager-0.4.14.dist-info/WHEEL
napari_boxmanager-0.4.14.dist-info/entry_points.txt
napari_boxmanager-0.4.14.dist-info/top_level.txt
napari_boxmanager-0.4.14.dist-info/RECORD
