Metadata-Version: 2.1
Name: napari-boxmanager
Version: 0.4.14
Summary: Particle selection tool for cryo-em
Home-page: https://github.com/MPI-Dortmund/napari-boxmanager
Author: Markus Stabrin
Author-email: markus.stabrin@mpi-dortmund.mpg.de
License: MPL-2.0
Classifier: Development Status :: 2 - Pre-Alpha
Classifier: Framework :: napari
Classifier: Intended Audience :: Developers
Classifier: License :: OSI Approved :: Mozilla Public License 2.0 (MPL 2.0)
Classifier: Operating System :: OS Independent
Classifier: Programming Language :: Python
Classifier: Programming Language :: Python :: 3
Classifier: Programming Language :: Python :: 3 :: Only
Classifier: Programming Language :: Python :: 3.10
Classifier: Topic :: Software Development :: Testing
Requires-Python: >=3.10
License-File: LICENSE
Requires-Dist: matplotlib
Requires-Dist: mrcfile
Requires-Dist: numpy<=1.23.5
Requires-Dist: pystardb>=0.4.2
Requires-Dist: napari>=0.4.17
Requires-Dist: pandas
Requires-Dist: scipy
Requires-Dist: tifffile
Requires-Dist: tqdm
Provides-Extra: testing
Requires-Dist: mrcfile; extra == "testing"
Requires-Dist: napari; extra == "testing"
Requires-Dist: pyqt5; extra == "testing"
Requires-Dist: pytest; extra == "testing"
Requires-Dist: pytest-cov; extra == "testing"
Requires-Dist: pytest-qt; extra == "testing"
Requires-Dist: tox; extra == "testing"
